receipt_parser/__init__.py
receipt_parser/cat_model.py
receipt_parser/dicts.py
receipt_parser/finder.py
receipt_parser/normalizer.py
receipt_parser/receipt_parser.py
receipt_parser-0.0.28.dist-info/LICENSE
receipt_parser-0.0.28.dist-info/METADATA
receipt_parser-0.0.28.dist-info/WHEEL
receipt_parser-0.0.28.dist-info/top_level.txt
receipt_parser-0.0.28.dist-info/RECORD
