Metadata-Version: 2.1
Name: receipt-parser
Version: 0.0.28
Summary: Allow receipt parsing
Home-page: https://github.com/slgero/receipt_parser
Author: Savvov Sergey
Author-email: sersavvov@yandex.ru
License: UNKNOWN
Keywords: receipt parser,product parser,nlp
Platform: UNKNOWN
Classifier: Programming Language :: Python :: 3
Classifier: License :: OSI Approved :: MIT License
Classifier: Operating System :: OS Independent
Classifier: Intended Audience :: Science/Research
Classifier: Topic :: Scientific/Engineering :: Information Analysis
Classifier: Natural Language :: Russian
Requires-Python: >=3.6
Requires-Dist: numpy (>=1.18.3)
Requires-Dist: pandas (>=1.0.3)
Requires-Dist: pandarallel (>=1.4.8)
Requires-Dist: pymystem3 (>=0.2.0)
Requires-Dist: setuptools
Requires-Dist: torch
Requires-Dist: torchvision
Requires-Dist: wget (>=3.2)
Requires-Dist: youtokentome (>=1.0.6)
